odoo/addons/mrp_workorder_lot_display/README.rst
odoo/addons/mrp_workorder_lot_display/__init__.py
odoo/addons/mrp_workorder_lot_display/__manifest__.py
odoo/addons/mrp_workorder_lot_display/i18n/fr.po
odoo/addons/mrp_workorder_lot_display/i18n/it.po
odoo/addons/mrp_workorder_lot_display/i18n/mrp_workorder_lot_display.pot
odoo/addons/mrp_workorder_lot_display/readme/CONTRIBUTORS.md
odoo/addons/mrp_workorder_lot_display/readme/DESCRIPTION.md
odoo/addons/mrp_workorder_lot_display/static/description/icon.png
odoo/addons/mrp_workorder_lot_display/static/description/index.html
odoo/addons/mrp_workorder_lot_display/views/mrp_workorder.xml
odoo_addon_mrp_workorder_lot_display-16.0.1.0.0.5.dist-info/METADATA
odoo_addon_mrp_workorder_lot_display-16.0.1.0.0.5.dist-info/WHEEL
odoo_addon_mrp_workorder_lot_display-16.0.1.0.0.5.dist-info/top_level.txt
odoo_addon_mrp_workorder_lot_display-16.0.1.0.0.5.dist-info/RECORD
